[
    {
    "id": 1,
    "price": 250,
    "name": "Hamburger",
    "tags": [{"name":"Burger"}, {"name": "Non Veg"}],
    "imageUrl": "../../assets/food1.png",
    "cookTime": 20,
    "description": "A mouthwatering fresh hamburger featuring succulent beef patty topped with gooey melted cheese, creating a perfect harmony of flavors and textures in every bite.",
    "stars": 4.8,
    "onSale": 0,
    "published": 1
  },
  {
    "id": 2,
    "price": 300,
    "name": "Salmon Poke Bowl",
    "tags": [{"name": "Non Veg"}],
    "imageUrl": "../../assets/food2.png",
    "cookTime": 15,
    "description": "A salmon poke bowl is a Hawaiian dish featuring marinated diced salmon served over rice or greens, topped with vegetables and flavorful sauces.",
    "stars": 3.5,
    "onSale": 0,
    "published": 1
  },
  {
    "price": 180,
    "name": "Chicken Biriyani",
    "categories": [
        {"id":"4147592a-deea-4d00-9f61-377ca1d26f2e","name": "Non Veg", "published" :1}, 
        {"id":"af23daf3-9d4b-4b37-b5c2-3c741852b7e9","name":"Biriyani", "published" :1}, 
        {"id":"ef476d62-5ea6-4575-bcfc-432f23316250","name" :"Indian", "published" :1}
    ],
    "imageUrl": "../../assets/food3.png",
    "cookTime": 30,
    "description": "Chicken biryani is a fragrant South Asian rice dish, combining marinated chicken, basmati rice, and aromatic spices in a flavorful medley.",
    "stars": 5.0,
    "onSale": 0,
    "published": 1
  },
  {
    "id": 4,
    "price": 250,
    "name": "Spaghetti Meatballs",
    "tags": [{"name": "Non Veg"}, "Pasta"],
    "imageUrl": "../../assets/food4.png",
    "cookTime": 30,
    "description": "Spaghetti meatballs is a classic Italian-American dish featuring tender meatballs made from ground meat, served over a bed of al dente spaghetti noodles, and topped with rich marinara sauce and grated cheese.",
    "stars": 3.7,
    "onSale": 0,
    "published": 1
  },
  {
    "id": 5,
    "price": 350,
    "name": "Mushroom Pizza",
    "tags": ["Veg", "Pizza"],
    "imageUrl": "../../assets/food5.png",
    "cookTime": 45,
    "description": "Mushroom pizza is a savory delight featuring a crispy crust topped with tomato sauce, cheese, and earthy, flavorful mushrooms, baked to perfection.",
    "stars": 4.3,
    "onSale": 0,
    "published": 1
  },
  {
    "id": 6,
    "price": 400,
    "name": "Farfalle Pasta",
    "tags": [{"name": "Non Veg"}, "Pasta"],
    "imageUrl": "../../assets/food6.png",
    "cookTime": 24,
    "description": "It is a delectable dish combining tender pasta bows, savory meatballs, and a creamy spinach-infused sauce for a rich and satisfying Italian meal.",
    "stars": 3.4,
    "onSale": 0,
    "published": 1
  },
  {
    "id": 7,
    "price": 200,
    "name": "French Fries With Cheese",
    "tags": ["Veg", "Quick Bites"],
    "imageUrl": "../../assets/food7.png",
    "cookTime": 15,
    "description": "A bowl of fries with cheese and sauce on top is a delicious indulgence featuring crispy fries smothered in melted cheese and flavorful sauces for a satisfying snack or appetizer.",
    "stars": 4.5,
    "onSale": 0,
    "published": 1
  },
  {
    "id": 8,
    "price": 320,
    "name": "Fried Crispy Shrimp",
    "tags": [{"name": "Non Veg"}, "Quick Bites", "Chinese"],
    "imageUrl": "../../assets/food8.png",
    "cookTime": 30,
    "description": "Succulent shrimp coated in a crunchy batter, deep-fried to golden perfection, creating a delicious and satisfying starter.",
    "stars": 4.5,
    "onSale": 0,
    "published": 1
  },
  {
    "id": 9,
    "price": 280,
    "name": "Roasted Chicken & Potatoes",
    "tags": [{"name": "Non Veg"}],
    "imageUrl": "../../assets/food9.png",
    "cookTime": 40,
    "description": "Roasted chicken with potatoes is a hearty dish where tender, succulent chicken is oven-baked alongside seasoned potatoes, resulting in a flavorful and comforting meal.",
    "stars": 2.4,
    "onSale": 0,
    "published": 1
  },
  {
    "id": 10,
    "price": 250,
    "name": "Egg Chicken Noodles",
    "tags": [{"name": "Non Veg"}, "Noodles", "Chinese"],
    "imageUrl": "../../assets/food10.png",
    "cookTime": 45,
    "description": "A stir-fried dish combining eggs, tender chicken pieces, vegetables, and noodles, seasoned with savory sauces for a flavorful Asian-inspired meal.",
    "stars": 4.2,
    "onSale": 0,
    "published": 1
  },
  {
    "id": 11,
    "price": 320,
    "name": "Stirfried Chicken Noodles",
    "tags": [{"name": "Non Veg"}, "Noodles", "Chinese"],
    "imageUrl": "../../assets/food_1.png",
    "cookTime": 30,
    "description": "A delicious Asian dish featuring tender chicken pieces, fresh vegetables, and flavorful noodles, cooked together in a savory stir-fry sauce.",
    "stars": 4.0,
    "onSale": 0,
    "published": 1
  },
  {
    "id": 12,
    "price": 170,
    "name": "Nuggets Meal",
    "tags": [{"name": "Non Veg"}, "Quick Bites"],
    "imageUrl": "../../assets/food_1.png",
    "cookTime": 25,
    "description": "Crispy bite-sized chicken pieces paired with golden, seasoned fries, a classic and satisfying fast-food favorite.",
    "stars": 4.0,
    "onSale": 0,
    "published": 1
  },
  {
    "id": 13,
    "price": 250,
    "name": "Beef Noodles",
    "tags": [{"name": "Non Veg"}, "Noodles", "Chinese"],
    "imageUrl": "../../assets/food_1.png",
    "cookTime": 40,
    "description": "Hearty and flavorful noodle featuring tender beef slices, noodles, a comforting dish enjoyed in various Asian cuisines.",
    "stars": 3.0,
    "onSale": 0,
    "published": 1
  },
  {
    "id": 14,
    "price": 250,
    "name": "Mushroom Noodles",
    "tags": ["Veg", "Noodles", "Chinese"],
    "imageUrl": "../../assets/food_1.png",
    "cookTime": 40,
    "description": "Stir-fried noodles infused with earthy mushrooms, creating a flavorful and satisfying Asian dish.",
    "stars": 3.8,
    "onSale": 0,
    "published": 1
  },
  {
    "id": 15,
    "price": 270,
    "name": "Mushroom Soup Noodles",
    "tags": ["Veg", "Noodles", "Chinese", "Soup"],
    "imageUrl": "../../assets/food_1.png",
    "cookTime": 40,
    "description": "A comforting and flavorful Asian dish, combining tender noodles, savory broth, and assorted mushrooms for a hearty and satisfying meal.",
    "stars": 3.2,
    "onSale": 0,
    "published": 1
  },
  {
    "id": 16,
    "price": 300,
    "name": "Tofu Noodles Soup",
    "tags": ["Veg", "Noodles", "Chinese", "Soup"],
    "imageUrl": "../../assets/food_1.png",
    "cookTime": 35,
    "description": "A comforting Asian dish combining silky tofu, tender noodles, and fresh vegetables, all simmered in a flavorful broth for a hearty, satisfying meal.",
    "stars": 3.2,
    "onSale": 0,
    "published": 1
  },
  {
    "id": 17,
    "price": 200,
    "name": "Mushroom & Onion Soup",
    "tags": ["Veg", "Soup"],
    "imageUrl": "../../assets/food_1.png",
    "cookTime": 35,
    "description": "A comforting blend of earthy mushrooms, caramelized onions, and savory broth, creating a hearty and flavorful soup.",
    "stars": 4.7,
    "onSale": 0,
    "published": 1
  },
  {
    "id": 18,
    "price": 170,
    "name": "Pumpkin Soup",
    "tags": ["Veg", "Soup"],
    "imageUrl": "../../assets/food_1.png",
    "cookTime": 20,
    "description": "Pumpkin soup is a creamy and comforting dish made from pureed pumpkin, flavored with aromatic spices and herbs, creating a warm and flavorful soup.",
    "stars": 2.5,
    "onSale": 0,
    "published": 1
  },
  {
    "id": 19,
    "price": 230,
    "name": "Mutton Curry",
    "tags": [{"name": "Non Veg"}, {"name" :"Indian"}],
    "imageUrl": "../../assets/food_1.png",
    "cookTime": 45,
    "description": "Mutton curry is a flavorful and aromatic South Asian dish made with tender pieces of mutton (goat meat) cooked in a rich, spicy gravy with a blend of traditional spices.",
    "stars": 4.9,
    "onSale": 0,
    "published": 1
  },
  {
    "id": 20,
    "price": 220,
    "name": "Chicken Curry",
    "tags": [{"name": "Non Veg"}, {"name" :"Indian"}],
    "imageUrl": "../../assets/food_1.png",
    "cookTime": 30,
    "description": "Chicken curry is a delectable dish made with tender chicken pieces simmered in a fragrant and flavorful sauce, typically featuring a blend of spices, tomatoes, and coconut milk in various regional styles.",
    "stars": 4.7,
    "onSale": 0,
    "published": 1
  },
  {
    "id": 21,
    "price": 170,
    "name": "Submarine Sandwich",
    "tags": [{"name": "Non Veg"}, "Sandwich"],
    "imageUrl": "../../assets/food_1.png",
    "cookTime": 30,
    "description": "A submarine sandwich with ham, tomato, and onion is a flavorful deli creation, featuring layers of thinly sliced ham, fresh tomatoes, and crisp onions, served in a long, soft bread roll.",
    "stars": 4.1,
    "onSale": 0,
    "published": 1
  },
  {
    "id": 22,
    "price": 150,
    "name": "Spicy Chicken Sandwich",
    "tags": [{"name": "Non Veg"}, "Sandwich"],
    "imageUrl": "../../assets/food_1.png",
    "cookTime": 28,
    "description": "A spicy chicken sandwich is a zesty delight, featuring succulent, seasoned chicken breast, fried to perfection, and served in a bun with spicy sauces and crisp vegetables for a fiery kick.",
    "stars": 3.9,
    "onSale": 0,
    "published": 1
  },
  {
    "id": 23,
    "price": 200,
    "name": "Chicken Cheese Sandwich",
    "tags": [{"name": "Non Veg"}, "Sandwich"],
    "imageUrl": "../../assets/food_1.png",
    "cookTime": 25,
    "description": "It is a delicious combination of grilled or toasted bread slices filled with tender chicken pieces and melted cheese, creating a comforting and indulgent snack or meal.",
    "stars": 4.4,
    "onSale": 0,
    "published": 1
  },
  {
    "id": 24,
    "price": 230,
    "name": "Double Patty Cheeseburger",
    "tags": [{"name": "Non Veg"}, {"name":"Burger"}],
    "imageUrl": "../../assets/food_1.png",
    "cookTime": 25,
    "description": "A double patty cheeseburger is a indulgent delight featuring two beef patties layered with melted cheese, served in a bun with fresh vegetables, condiments, and flavor-packed sauces.",
    "stars": 3.5,
    "onSale": 0,
    "published": 1
  },
  {
    "id": 25,
    "price": 210,
    "name": "Pan Fried Chicken Momo",
    "tags": [{"name": "Non Veg"}, "Momo", "Chinese"],
    "imageUrl": "../../assets/food_1.png",
    "cookTime": 20,
    "description": "Steamed dumplings filled with succulent chicken, cheese, and aromatic spices, a delightful fusion of flavors in each bite.",
    "stars": 4.6,
    "onSale": 0,
    "published": 1
  },
  {
    "id": 26,
    "price": 230,
    "name": "Chicken Momo",
    "tags": [{"name": "Non Veg"}, "Momo", "Chinese"],
    "imageUrl": "../../assets/food_1.png",
    "cookTime": 20,
    "description": "Steamed dumplings filled with succulent chicken, and aromatic spices, a delightful fusion of flavors in each bite.",
    "stars": 4.3,
    "onSale": 0,
    "published": 1
  },
  {
    "id": 27,
    "price": 150,
    "name": "Veg Momo",
    "tags": ["Veg", "Momo", "Chinese"],
    "imageUrl": "../../assets/food_1.png",
    "cookTime": 20,
    "description": "It is a popular Tibetan dumpling filled with a delicious mixture of vegetables, wrapped in thin dough, and steamed to perfection, often served with a tangy dipping sauce.",
    "stars": 4.0,
    "onSale": 0,
    "published": 1
  },
  {
    "id": 28,
    "price": 240,
    "name": "Mutton Momo",
    "tags": [{"name": "Non Veg"}, "Momo", "Chinese"],
    "imageUrl": "../../assets/food_1.png",
    "cookTime": 28,
    "description": "Mutton momo is a delectable Tibetan delicacy, consisting of steamed dumplings filled with spiced minced mutton, served with dipping sauces, popular in South Asian cuisine.",
    "stars": 4.9,
    "onSale": 0,
    "published": 1
  },
  {
    "id": 29,
    "price": 500,
    "name": "Red Velvet Cake",
    "tags": [{"name": "Non Veg"}, "Cake"],
    "imageUrl": "../../assets/food_1.png",
    "cookTime": 60,
    "description": "Red velvet cake is a moist and velvety dessert, characterized by its deep red color and subtle chocolate flavor, typically layered with cream cheese frosting, making it a delightful and visually appealing treat.",
    "stars": 3.4,
    "onSale": 0,
    "published": 1
  },
  {
    "id": 30,
    "price": 400,
    "name": "Chocolate Cake",
    "tags": [{"name": "Non Veg"}, "Cake"],
    "imageUrl": "../../assets/food_1.png",
    "cookTime": 65,
    "description": "Chocolate cake is a decadent dessert delight, featuring moist and rich layers of cocoa-flavored cake filled and frosted with luscious chocolate icing.",
    "stars": 3.8,
    "onSale": 0,
    "published": 1
  },
  {
    "id": 31,
    "price": 140,
    "name": "Cheese Cake",
    "tags": [{"name": "Non Veg"}, "Cake"],
    "imageUrl": "../../assets/food_1.png",
    "cookTime": 65,
    "description": "Cheesecake is a velvety dessert made with a creamy, cheese-based filling on a graham cracker crust, often topped with fruit, chocolate, or caramel for a delightful treat.",
    "stars": 2.4,
    "onSale": 0,
    "published": 1
  },
  {
    "id": 32,
    "price": 170,
    "name": "Carrot Cake",
    "tags": [{"name": "Non Veg"}, "Cake"],
    "imageUrl": "../../assets/food_1.png",
    "cookTime": 40,
    "description": "Carrot cake is a moist and spiced dessert made with grated carrots, often containing nuts or raisins, and topped with cream cheese frosting, offering a delightful balance of flavors.",
    "stars": 4.3,
    "onSale": 0,
    "published": 1
  },
  {
    "id": 33,
    "price": 180,
    "name": "Blueberry Cheese Cake",
    "tags": [{"name": "Non Veg"}, "Cake"],
    "imageUrl": "../../assets/food_1.png",
    "cookTime": 50,
    "description": "Blueberry cheesecake is a delectable dessert that combines a velvety, creamy cheesecake filling with a sweet and tangy blueberry topping, all nestled on a buttery graham cracker crust.",
    "stars": 4.7,
    "onSale": 0,
    "published": 1
  },
  {
    "id": 34,
    "price": 300,
    "name": "Cheesy Mushroom Pasta",
    "tags": ["Veg", "Pasta"],
    "imageUrl": "../../assets/food_1.png",
    "cookTime": 30,
    "description": "It is a creamy and indulgent Italian dish, combining al dente pasta with sautéed mushrooms, tossed in a velvety cheese sauce for a comforting and flavorful meal.",
    "stars": 4.7,
    "onSale": 0,
    "published": 1
  },
  {
    "id": 35,
    "price": 280,
    "name": "Red Sauce Pasta",
    "tags": ["Veg", "Pasta"],
    "imageUrl": "../../assets/food_1.png",
    "cookTime": 30,
    "description": "Red sauce pasta is a classic Italian dish featuring al dente pasta coated in a flavorful tomato-based sauce, often infused with garlic, herbs, and sometimes chili flakes, delivering a delicious and comforting meal.",
    "stars": 4.1,
    "onSale": 0,
    "published": 1
  },
  {
    "id": 36,
    "price": 330,
    "name": "Rotini Pasta Salad",
    "tags": ["Veg", "Pasta", "Salad"],
    "imageUrl": "../../assets/food_1.png",
    "cookTime": 30,
    "description": "Rotini pasta salad is a colorful and refreshing dish, combining spiral-shaped pasta with vibrant vegetables, cheese, and a zesty dressing, perfect for picnics and gatherings.",
    "stars": 4.6,
    "onSale": 10
  },
  {
    "id": 37,
    "price": 250,
    "name": "Macaroni Pasta Salad",
    "tags": ["Veg", "Pasta", "Salad"],
    "imageUrl": "../../assets/food_1.png",
    "cookTime": 35,
    "description": "A delightful blend of cooked macaroni, crisp vegetables, and creamy dressing, creating a refreshing and satisfying dish.",
    "stars": 3.4,
    "onSale": 5
  },
  {
    "id": 38,
    "price": 280,
    "name": "Pappardelle Pasta",
    "tags": [{"name": "Non Veg"}, "Pasta"],
    "imageUrl": "../../assets/food_1.png",
    "cookTime": 42,
    "description": "Wide, ribbon-like noodles paired with rich sauces, creating a luxurious and satisfying Italian meal.",
    "stars": 4.3,
    "onSale": 4
  },
  {
    "id": 39,
    "price": 250,
    "name": "Indian Sweets Platter",
    "tags": ["Veg", "Deserts"],
    "imageUrl": "../../assets/food_1.png",
    "cookTime": 35,
    "description": "A delightful assortment of traditional sweets showcasing the rich flavors and textures of Indian desserts, perfect for celebrations and festivals.",
    "stars": 4.4,
    "onSale": 5
  },
  {
    "id": 40,
    "price": 170,
    "name": "Macarons",
    "tags": ["Veg", "Deserts"],
    "imageUrl": "../../assets/food_1.png",
    "cookTime": 35,
    "description": "These are delicate, colorful French confections made from almond flour meringue shells, sandwiched together with a variety of flavorful fillings, creating a sweet and airy treat.",
    "stars": 4.6,
    "onSale": 10
  },
  {
    "id": 41,
    "price": 180,
    "name": "Choco Vanilla Ice Cream",
    "tags": ["Veg", "Deserts"],
    "imageUrl": "../../assets/food_1.png",
    "cookTime": 20,
    "description": "Choco vanilla ice cream is a delightful treat featuring swirls of rich chocolate and creamy vanilla flavors, perfect for satisfying sweet cravings.",
    "stars": 4.8,
    "onSale": 20
  },
  {
    "id": 42,
    "price": 150,
    "name": "Caramel Vanilla Ice Cream",
    "tags": ["Veg", "Deserts"],
    "imageUrl": "../../assets/food_1.png",
    "cookTime": 20,
    "description": "Creamy vanilla base swirled with ribbons of rich caramel, creating a perfect blend of sweetness and indulgence.",
    "stars": 4.5,
    "onSale": 10
  },
  {
    "id": 43,
    "price": 600,
    "name": "Oreo Cake",
    "tags": [{"name": "Non Veg"}, "Cake"],
    "imageUrl": "../../assets/food_1.png",
    "cookTime": 80,
    "description": "Indulgent dessert featuring layers of moist chocolate cake, creamy Oreo-flavored filling, and crumbled cookies for a delightful crunch.",
    "stars": 4.7,
    "onSale": 6
  },
  {
    "id": 44,
    "price": 450,
    "name": "Figs Cake",
    "tags": [{"name": "Non Veg"}, "Cake"],
    "imageUrl": "../../assets/food_1.png",
    "cookTime": 80,
    "description": "A moist and indulgent dessert featuring sweet figs baked into a delectable cake, offering a delightful blend of flavors.",
    "stars": 3.7,
    "onSale": 4
  },
  {
    "id": 45,
    "price": 650,
    "name": "Strawberry Cheesecake",
    "tags": [{"name": "Non Veg"}, "Cake"],
    "imageUrl": "../../assets/food_1.png",
    "cookTime": 80,
    "description": "Creamy, decadent dessert featuring a velvety cheesecake filling atop a graham cracker crust, adorned with fresh, luscious strawberries.",
    "stars": 4.2,
    "onSale": 10
  },
  {
    "id": 46,
    "price": 550,
    "name": "Chocolate Fudge Cake",
    "tags": [{"name": "Non Veg"}, "Cake"],
    "imageUrl": "../../assets/food_1.png",
    "cookTime": 90,
    "description": "Indulgent dessert with dense, moist chocolate layers and a smooth, velvety fudge frosting.",
    "stars": 4.6,
    "onSale": 20
  },
  {
    "id": 47,
    "price": 750,
    "name": "Pineapple Cake",
    "tags": [{"name": "Non Veg"}, "Cake"],
    "imageUrl": "../../assets/food_1.png",
    "cookTime": 90,
    "description": "Moist and fruity dessert featuring layers of sponge cake filled with pineapple-flavored filling and frosting, a tropical delight.",
    "stars": 4.8,
    "onSale": 10
  },
  {
    "id": 48,
    "price": 180,
    "name": "Cold Brew Coffee",
    "tags": ["Beverages"],
    "imageUrl": "../../assets/food_1.png",
    "cookTime": 30,
    "description": "Smooth and refreshing, brewed with cold water over an extended period, resulting in a less acidic, naturally sweet, and highly caffeinated drink.",
    "stars": 4.4,
    "onSale": 5
  },
  {
    "id": 49,
    "price": 280,
    "name": "Pineapple Tequila Cocktail",
    "tags": ["Beverages"],
    "imageUrl": "../../assets/food_1.png",
    "cookTime": 20,
    "description": "A tropical blend of refreshing pineapple juice and smooth tequila, creating a vibrant and zesty cocktail experience.",
    "stars": 4.4,
    "onSale": 20
  },
  {
    "id": 50,
    "price": 280,
    "name": "Caipirinha Cocktail",
    "tags": ["Beverages"],
    "imageUrl": "../../assets/food_1.png",
    "cookTime": 20,
    "description": "A Brazilian classic made with cachaça, fresh lime, sugar, and ice, offering a refreshing and citrusy taste.",
    "stars": 4.7,
    "onSale": 10
  }
]